primitiveDB/__init__.py
primitiveDB/client/Client.py
primitiveDB/client/__init__.py
primitiveDB/server/Server.py
primitiveDB/server/__init__.py
primitiveDB-0.0.2.dist-info/LICENSE.txt
primitiveDB-0.0.2.dist-info/METADATA
primitiveDB-0.0.2.dist-info/WHEEL
primitiveDB-0.0.2.dist-info/top_level.txt
primitiveDB-0.0.2.dist-info/RECORD
