Metadata-Version: 2.1
Name: primitiveDB
Version: 0.0.2
Summary: An easy-to-use databasing library
Home-page: UNKNOWN
Author: Fahim Ferdous (Capt.Pyrite)
Author-email: <liveviewer360@gmail.com>
License: UNKNOWN
Keywords: python,flask,pandas,database
Platform: UNKNOWN
Classifier: Development Status :: 2 - Pre-Alpha
Classifier: Intended Audience :: Developers
Classifier: Programming Language :: Python :: 3
Classifier: Operating System :: Unix
Classifier: Operating System :: Microsoft :: Windows
License-File: LICENSE.txt
Requires-Dist: Flask (==2.2.2)
Requires-Dist: httpx (==0.23.2)
Requires-Dist: pandas (==1.5.0)
Requires-Dist: py-cpuinfo (==9.0.0)
